pythonmatrix/__init__.py
pythonmatrix-0.0.1.dist-info/LICENSE.txt
pythonmatrix-0.0.1.dist-info/METADATA
pythonmatrix-0.0.1.dist-info/WHEEL
pythonmatrix-0.0.1.dist-info/top_level.txt
pythonmatrix-0.0.1.dist-info/RECORD
