Metadata-Version: 2.1
Name: pythonmatrix
Version: 0.0.1
Summary: This is a small Matrix Library.
Home-page: https://github.com/Deadpool4099/pymat
Author: Tejaswi Kompella
Author-email: tejakompella@gmail.com
License: MIT
Platform: UNKNOWN
Classifier: Programming Language :: Python :: 3
Classifier: License :: OSI Approved :: MIT License
Classifier: Operating System :: OS Independent
Requires-Dist: numpy
Requires-Dist: scipy
